{
    "$schema": "../schema/recording.json",
    "title": "S01E56 - Jam 3",
    "recorded_date": "unknown",
    "data_folder": "S01E56-J3",
    "stereo_mix": {
        "id": 17,
        "name": "Stereo mix",
        "flac": "S01E56-J3_stereo.flac",
        "vorbis": "ogg/S01E56-J3_stereo.ogg",
        "mp3": "mp3/{FLACBASE}.mp3"
    },
    "tags": [
        "tbd"
    ],
    "tracks": [
        {
            "id": 1,
            "name": "Bass",
            "flac": "Colin Benders - Day 56 Jam 3 -  bass.flac",
            "vorbis": "ogg/{FLACBASE}.ogg",
            "mp3": "mp3/{FLACBASE}.mp3"
        },
        {
            "id": 2,
            "name": "BD",
            "flac": "Colin Benders - Day 56 Jam 3 -  BD.flac",
            "vorbis": "ogg/{FLACBASE}.ogg",
            "mp3": "mp3/{FLACBASE}.mp3"
        },
        {
            "id": 3,
            "name": "dly L",
            "flac": "Colin Benders - Day 56 Jam 3 -  dly L.flac",
            "vorbis": "ogg/{FLACBASE}.ogg",
            "mp3": "mp3/{FLACBASE}.mp3"
        },
        {
            "id": 4,
            "name": "dly R",
            "flac": "Colin Benders - Day 56 Jam 3 -  dly R.flac",
            "vorbis": "ogg/{FLACBASE}.ogg",
            "mp3": "mp3/{FLACBASE}.mp3"
        },
        {
            "id": 5,
            "name": "perc 2 L",
            "flac": "Colin Benders - Day 56 Jam 3 -  perc 2 L.flac",
            "vorbis": "ogg/{FLACBASE}.ogg",
            "mp3": "mp3/{FLACBASE}.mp3"
        },
        {
            "id": 6,
            "name": "perc 2 R",
            "flac": "Colin Benders - Day 56 Jam 3 -  perc 2 R.flac",
            "vorbis": "ogg/{FLACBASE}.ogg",
            "mp3": "mp3/{FLACBASE}.mp3"
        },
        {
            "id": 7,
            "name": "perc",
            "flac": "Colin Benders - Day 56 Jam 3 -  perc.flac",
            "vorbis": "ogg/{FLACBASE}.ogg",
            "mp3": "mp3/{FLACBASE}.mp3"
        },
        {
            "id": 8,
            "name": "rev L",
            "flac": "Colin Benders - Day 56 Jam 3 -  rev L.flac",
            "vorbis": "ogg/{FLACBASE}.ogg",
            "mp3": "mp3/{FLACBASE}.mp3"
        },
        {
            "id": 9,
            "name": "rev R",
            "flac": "Colin Benders - Day 56 Jam 3 -  rev R.flac",
            "vorbis": "ogg/{FLACBASE}.ogg",
            "mp3": "mp3/{FLACBASE}.mp3"
        },
        {
            "id": 10,
            "name": "synth 1",
            "flac": "Colin Benders - Day 56 Jam 3 -  synth 1.flac",
            "vorbis": "ogg/{FLACBASE}.ogg",
            "mp3": "mp3/{FLACBASE}.mp3"
        },
        {
            "id": 11,
            "name": "synth 2",
            "flac": "Colin Benders - Day 56 Jam 3 -  synth 2.flac",
            "vorbis": "ogg/{FLACBASE}.ogg",
            "mp3": "mp3/{FLACBASE}.mp3"
        },
        {
            "id": 13,
            "name": "synth 3",
            "flac": "Colin Benders - Day 56 Jam 3 -  synth 3.flac",
            "vorbis": "ogg/{FLACBASE}.ogg",
            "mp3": "mp3/{FLACBASE}.mp3"
        }
    ]
}